{"http://rdfs.org/ns/void#inDataset": ["http://objects.mainzed.org/data/ex_dataset"], "http://www.w3.org/1999/02/22-rdf-syntax-ns#type": ["http://www.w3.org/ns/prov-o/Activity"], "http://www.w3.org/2000/01/rdf-schema#label": ["Messreihe 0 Messvorgang 1 Kalibrierung ", "MS 0 Measurement 1 Calibration Activity "], "http://www.w3.org/ns/prov-o/used": ["http://objects.mainzed.org/data/d4e1fb47-f2a2-df0f-6725-668613510cc6_ms_0_measurement1_calibration_object"], "http://www.w3.org/ns/prov-o/wasAssociatedWith": ["http://objects.mainzed.org/data/29835bbe-f2d9-8caa-5761-b40f2757c7da"]}