{"http://objects.mainzed.org/ont#commonReferencepoint": ["false"], "http://objects.mainzed.org/ont#pointID": ["84"], "http://objects.mainzed.org/ont#pointMeasurementDeviation": ["http://objects.mainzed.org/data/12c19a17-99f9-04ed-a68d-6398bc1a3459_ms_1_measurement1_rp84_r_dev"], "http://objects.mainzed.org/ont#pointMeasurementState": ["ok"], "http://objects.mainzed.org/ont#pointProjectState": ["photogrammetric point"], "http://objects.mainzed.org/ont#xCoordinate": ["http://objects.mainzed.org/data/12c19a17-99f9-04ed-a68d-6398bc1a3459_ms_1_measurement1_rp84_r_x"], "http://objects.mainzed.org/ont#yCoordinate": ["http://objects.mainzed.org/data/12c19a17-99f9-04ed-a68d-6398bc1a3459_ms_1_measurement1_rp84_r_y"], "http://objects.mainzed.org/ont#zCoordinate": ["http://objects.mainzed.org/data/12c19a17-99f9-04ed-a68d-6398bc1a3459_ms_1_measurement1_rp84_r_z"], "http://rdfs.org/ns/void#inDataset": ["http://objects.mainzed.org/data/ex_dataset"], "http://www.gigamesh.eu/ont#selected": ["false"], "http://www.opengis.net/ont/geosparql#asWKT": ["POINT(191.96009887 -102.045979883 -49.911208762)"], "http://www.opengis.net/ont/geosparql#inSRS": ["http://objects.mainzed.org/data/cs_3d_x_millimetre_y_millimetre_z_millimetre"], "http://www.w3.org/1999/02/22-rdf-syntax-ns#type": ["http://www.gigamesh.eu/ont#ReferencePoint"], "http://www.w3.org/2000/01/rdf-schema#label": ["RP84 ( Messreihe 1 Messung 1)", "RP84 ( MS 1 Measurement 1)"], "http://www.w3.org/ns/prov-o/wasAttributedTo": ["http://objects.mainzed.org/data/12c19a17-99f9-04ed-a68d-6398bc1a3459_ms_1_measurement1_algorithm"], "http://www.w3.org/ns/prov-o/wasGeneratedBy": ["http://objects.mainzed.org/data/12c19a17-99f9-04ed-a68d-6398bc1a3459_ms_1_measurement1_activity"]}