{"http://objects.mainzed.org/ont#commonReferencepoint": ["false"], "http://objects.mainzed.org/ont#pointMeasurementDeviation": ["http://objects.mainzed.org/data/d4e1fb47-f2a2-df0f-6725-668613510cc6_ms_0_measurement1_rp_noid_1_r_dev"], "http://objects.mainzed.org/ont#pointMeasurementState": ["outside"], "http://objects.mainzed.org/ont#pointProjectState": ["photogrammetric point"], "http://objects.mainzed.org/ont#xCoordinate": ["http://objects.mainzed.org/data/d4e1fb47-f2a2-df0f-6725-668613510cc6_ms_0_measurement1_rp_noid_1_r_x"], "http://objects.mainzed.org/ont#yCoordinate": ["http://objects.mainzed.org/data/d4e1fb47-f2a2-df0f-6725-668613510cc6_ms_0_measurement1_rp_noid_1_r_y"], "http://objects.mainzed.org/ont#zCoordinate": ["http://objects.mainzed.org/data/d4e1fb47-f2a2-df0f-6725-668613510cc6_ms_0_measurement1_rp_noid_1_r_z"], "http://rdfs.org/ns/void#inDataset": ["http://objects.mainzed.org/data/ex_dataset"], "http://www.opengis.net/ont/geosparql#asWKT": ["POINT(189.767402867 195.715896312 -373.427961038)"], "http://www.w3.org/1999/02/22-rdf-syntax-ns#type": ["http://objects.mainzed.org/ont#ReferencePoint"], "http://www.w3.org/2000/01/rdf-schema#label": ["RP_noid_1 ( MS 0 Measurement 1)", "RP_noid_1 ( Messreihe 0 Messung 1)"], "http://www.w3.org/ns/prov-o/wasAttributedTo": ["http://objects.mainzed.org/data/d4e1fb47-f2a2-df0f-6725-668613510cc6_ms_0_measurement1_algorithm"], "http://www.w3.org/ns/prov-o/wasGeneratedBy": ["http://objects.mainzed.org/data/d4e1fb47-f2a2-df0f-6725-668613510cc6_ms_0_measurement1_activity"]}